numerator/__init__.py
numerator/main.py
numerator/test_main.py
numerator-1.0.1.dist-info/LICENSE
numerator-1.0.1.dist-info/METADATA
numerator-1.0.1.dist-info/WHEEL
numerator-1.0.1.dist-info/entry_points.txt
numerator-1.0.1.dist-info/top_level.txt
numerator-1.0.1.dist-info/RECORD
