Metadata-Version: 2.1
Name: numerator
Version: 1.0.1
Summary: Script that automatically renames files, so they get equally zero left padded names
Author-email: Igor Zyktin <nicord@yandex.ru>
Project-URL: Homepage, https://github.com/IgorZyktin/numerator
Classifier: Programming Language :: Python :: 3
Classifier: License :: OSI Approved :: MIT License
Classifier: Operating System :: OS Independent
Requires-Python: >=3.7
License-File: LICENSE
